<library path="lib/libmy_controller_pkg">

    <class name="my_controller_pkg/SimpleController" type="my_controller_pkg::SimpleController" base_class_type="controller_interface::ControllerBase">
        <description>
            The effort test controller expects a JointEffortCommandInterface type of hardware interface.
        </description>
    </class>

    <class name="my_controller_pkg/ArmController" type="my_controller_pkg::ArmController" base_class_type="controller_interface::ControllerBase">
        <description>
            The effort controller expects a JointEffortCommandInterface type of hardware interface.
        </description>
    </class>

    <class name="my_controller_pkg/WheelController" type="my_controller_pkg::WheelController" base_class_type="controller_interface::ControllerBase">
        <description>
            The effort controller expects a JointEffortCommandInterface type of hardware interface.
        </description>
    </class>

    <class name="my_controller_pkg/MobileController" type="my_controller_pkg::MobileController" base_class_type="controller_interface::ControllerBase">
        <description>
            The effort controller expects a JointEffortCommandInterface type of hardware interface.
        </description>
    </class>

</library>
